LICENCE
README.md
setup.py
distribute_logging/__init__.py
distribute_logging.egg-info/PKG-INFO
distribute_logging.egg-info/SOURCES.txt
distribute_logging.egg-info/dependency_links.txt
distribute_logging.egg-info/requires.txt
distribute_logging.egg-info/top_level.txt
distribute_logging.egg-info/zip-safe
distribute_logging/portalocker/__init__.py
distribute_logging/portalocker/constants.py
distribute_logging/portalocker/exceptions.py
distribute_logging/portalocker/portalocker.py
distribute_logging/portalocker/queue.py
distribute_logging/portalocker/utils.py